synthbiodata/__init__.py
synthbiodata/constants.py
synthbiodata/exceptions.py
synthbiodata/factory.py
synthbiodata/logging.py
synthbiodata/config/__init__.py
synthbiodata/config/base.py
synthbiodata/config/schema/__init__.py
synthbiodata/config/schema/v1/__init__.py
synthbiodata/config/schema/v1/adme.py
synthbiodata/config/schema/v1/molecular.py
synthbiodata/core/__init__.py
synthbiodata/core/adme.py
synthbiodata/core/base.py
synthbiodata/core/molecular.py
synthbiodata-0.0.1a0.dist-info/METADATA
synthbiodata-0.0.1a0.dist-info/WHEEL
synthbiodata-0.0.1a0.dist-info/RECORD
