Metadata-Version: 2.4
Name: synthbiodata
Version: 0.0.1a0
Summary: A synthetic data generator for drug discovery machine learning
Project-URL: Homepage, https://github.com/ojeda-e/synthbiodata
Project-URL: Repository, https://github.com/ojeda-e/synthbiodata.git
Project-URL: Documentation, https://ojeda-e.com/synthbiodata/
Author-email: Estefania Barreto-Ojeda <ojeda-e@gmail.com>
License-Expression: MIT
Classifier: Development Status :: 3 - Alpha
Classifier: Intended Audience :: Science/Research
Classifier: License :: OSI Approved :: MIT License
Classifier: Programming Language :: Python :: 3
Classifier: Programming Language :: Python :: 3.10
Classifier: Programming Language :: Python :: 3.11
Classifier: Programming Language :: Python :: 3.12
Classifier: Programming Language :: Python :: 3.13
Classifier: Topic :: Scientific/Engineering :: Bio-Informatics
Classifier: Topic :: Scientific/Engineering :: Chemistry
Requires-Python: >=3.10
Requires-Dist: faker>=8.0.0
Requires-Dist: numpy>=1.21.0
Requires-Dist: polars>=0.19.0
Requires-Dist: pydantic>=2.5.0
